nibiru/__init__.py
nibiru/client.py
nibiru/common.py
nibiru/composer.py
nibiru/constant.py
nibiru/exceptions.py
nibiru/network.py
nibiru/sdk.py
nibiru/test_utils.py
nibiru/transaction.py
nibiru/utils.py
nibiru/wallet.py
nibiru/clients/__init__.py
nibiru/clients/dex.py
nibiru/clients/perp.py
nibiru/clients/pricefeed.py
nibiru/clients/util.py
nibiru/clients/vpool.py
nibiru/composers/__init__.py
nibiru/composers/pricefeed.py
nibiru/proto/__init__.py
nibiru/proto/common/common_pb2.py
nibiru/proto/common/common_pb2_grpc.py
nibiru/proto/confio/proofs_pb2.py
nibiru/proto/confio/proofs_pb2_grpc.py
nibiru/proto/cosmos/auth/v1beta1/auth_pb2.py
nibiru/proto/cosmos/auth/v1beta1/auth_pb2_grpc.py
nibiru/proto/cosmos/auth/v1beta1/genesis_pb2.py
nibiru/proto/cosmos/auth/v1beta1/genesis_pb2_grpc.py
nibiru/proto/cosmos/auth/v1beta1/query_pb2.py
nibiru/proto/cosmos/auth/v1beta1/query_pb2_grpc.py
nibiru/proto/cosmos/authz/v1beta1/authz_pb2.py
nibiru/proto/cosmos/authz/v1beta1/authz_pb2_grpc.py
nibiru/proto/cosmos/authz/v1beta1/event_pb2.py
nibiru/proto/cosmos/authz/v1beta1/event_pb2_grpc.py
nibiru/proto/cosmos/authz/v1beta1/genesis_pb2.py
nibiru/proto/cosmos/authz/v1beta1/genesis_pb2_grpc.py
nibiru/proto/cosmos/authz/v1beta1/query_pb2.py
nibiru/proto/cosmos/authz/v1beta1/query_pb2_grpc.py
nibiru/proto/cosmos/authz/v1beta1/tx_pb2.py
nibiru/proto/cosmos/authz/v1beta1/tx_pb2_grpc.py
nibiru/proto/cosmos/bank/v1beta1/authz_pb2.py
nibiru/proto/cosmos/bank/v1beta1/authz_pb2_grpc.py
nibiru/proto/cosmos/bank/v1beta1/bank_pb2.py
nibiru/proto/cosmos/bank/v1beta1/bank_pb2_grpc.py
nibiru/proto/cosmos/bank/v1beta1/genesis_pb2.py
nibiru/proto/cosmos/bank/v1beta1/genesis_pb2_grpc.py
nibiru/proto/cosmos/bank/v1beta1/query_pb2.py
nibiru/proto/cosmos/bank/v1beta1/query_pb2_grpc.py
nibiru/proto/cosmos/bank/v1beta1/tx_pb2.py
nibiru/proto/cosmos/bank/v1beta1/tx_pb2_grpc.py
nibiru/proto/cosmos/base/abci/v1beta1/abci_pb2.py
nibiru/proto/cosmos/base/abci/v1beta1/abci_pb2_grpc.py
nibiru_py-0.0.15.dist-info/LICENSE
nibiru_py-0.0.15.dist-info/METADATA
nibiru_py-0.0.15.dist-info/WHEEL
nibiru_py-0.0.15.dist-info/top_level.txt
nibiru_py-0.0.15.dist-info/RECORD
