Metadata-Version: 2.1
Name: nibiru-py
Version: 0.0.15
Summary: Nibiru Python SDK
Home-page: https://github.com/NibiruChain/nibiru-py
Author: Nibiru Chain
Author-email: dev@nibiru.fi
License: Apache Software License 2.0
Platform: UNKNOWN
Classifier: License :: OSI Approved :: Apache Software License
Classifier: Programming Language :: Python
Classifier: Programming Language :: Python :: 3
Classifier: Programming Language :: Python :: 3.7
Classifier: Programming Language :: Python :: Implementation :: CPython
Classifier: Programming Language :: Python :: Implementation :: PyPy
Requires-Python: >=3.9.0
License-File: LICENSE
Requires-Dist: grpcio
Requires-Dist: asyncio
Requires-Dist: aiohttp
Requires-Dist: ecdsa
Requires-Dist: bech32
Requires-Dist: mnemonic
Requires-Dist: hdwallets
Requires-Dist: pysha3
Requires-Dist: protobuf
Requires-Dist: grpcio-tools
Requires-Dist: bip32
Requires-Dist: requests
Requires-Dist: eip712-structs
Requires-Dist: coincurve
Requires-Dist: aiocron
Requires-Dist: python-dotenv
